refinire_tool_tavily/__init__.py
refinire_tool_tavily/api.py
refinire_tool_tavily/config.py
refinire_tool_tavily/models.py
refinire_tool_tavily/oneenv_template.py
refinire_tool_tavily/service.py
refinire_tool_tavily/tools.py
refinire_tool_tavily-0.1.0.dist-info/METADATA
refinire_tool_tavily-0.1.0.dist-info/WHEEL
refinire_tool_tavily-0.1.0.dist-info/entry_points.txt
refinire_tool_tavily-0.1.0.dist-info/top_level.txt
refinire_tool_tavily-0.1.0.dist-info/RECORD
