Metadata-Version: 2.4
Name: refinire-tool-tavily
Version: 0.1.0
Summary: Web search tool for RefinireAgent using Tavily API
Requires-Python: >=3.10
Requires-Dist: oneenv>=0.3.1
Requires-Dist: pydantic>=2.11.7
Requires-Dist: python-dotenv>=1.1.1
Requires-Dist: refinire>=0.2.11
Requires-Dist: tavily-python>=0.7.9
